<annotation>
	<folder></folder>
	<filename>f6bd07ef683431552cfab5a3f314fa26_jpg.rf.783fedb4da6e9825c5454cd526f48f42.jpg</filename>
	<path>f6bd07ef683431552cfab5a3f314fa26_jpg.rf.783fedb4da6e9825c5454cd526f48f42.jpg</path>
	<source>
		<database>roboflow.ai</database>
	</source>
	<size>
		<width>416</width>
		<height>416</height>
		<depth>3</depth>
	</size>
	<segmented>0</segmented>
	<object>
		<name>C17</name>
		<pose>Unspecified</pose>
		<truncated>0</truncated>
		<difficult>0</difficult>
		<occluded>0</occluded>
		<bndbox>
			<xmin>68</xmin>
			<xmax>219</xmax>
			<ymin>38</ymin>
			<ymax>204</ymax>
		</bndbox>
	</object>
</annotation>
