<annotation>
	<folder></folder>
	<filename>9607b7490a92847f702ac8237e9e14fb_jpg.rf.a5c56259b133cbab009d96d94c43ba8d.jpg</filename>
	<path>9607b7490a92847f702ac8237e9e14fb_jpg.rf.a5c56259b133cbab009d96d94c43ba8d.jpg</path>
	<source>
		<database>roboflow.ai</database>
	</source>
	<size>
		<width>416</width>
		<height>416</height>
		<depth>3</depth>
	</size>
	<segmented>0</segmented>
	<object>
		<name>F16</name>
		<pose>Unspecified</pose>
		<truncated>0</truncated>
		<difficult>0</difficult>
		<occluded>0</occluded>
		<bndbox>
			<xmin>22</xmin>
			<xmax>118</xmax>
			<ymin>33</ymin>
			<ymax>127</ymax>
		</bndbox>
	</object>
	<object>
		<name>A10</name>
		<pose>Unspecified</pose>
		<truncated>0</truncated>
		<difficult>0</difficult>
		<occluded>0</occluded>
		<bndbox>
			<xmin>154</xmin>
			<xmax>284</xmax>
			<ymin>94</ymin>
			<ymax>197</ymax>
		</bndbox>
	</object>
	<object>
		<name>F22</name>
		<pose>Unspecified</pose>
		<truncated>0</truncated>
		<difficult>0</difficult>
		<occluded>0</occluded>
		<bndbox>
			<xmin>103</xmin>
			<xmax>249</xmax>
			<ymin>134</ymin>
			<ymax>274</ymax>
		</bndbox>
	</object>
	<object>
		<name>F4</name>
		<pose>Unspecified</pose>
		<truncated>0</truncated>
		<difficult>0</difficult>
		<occluded>0</occluded>
		<bndbox>
			<xmin>282</xmin>
			<xmax>401</xmax>
			<ymin>242</ymin>
			<ymax>373</ymax>
		</bndbox>
	</object>
</annotation>
