<annotation>
	<folder></folder>
	<filename>b282ce2151ef350158745a9ab27b1508_jpg.rf.4cffb15ff60d9cb2604f37e78962257f.jpg</filename>
	<path>b282ce2151ef350158745a9ab27b1508_jpg.rf.4cffb15ff60d9cb2604f37e78962257f.jpg</path>
	<source>
		<database>roboflow.ai</database>
	</source>
	<size>
		<width>416</width>
		<height>416</height>
		<depth>3</depth>
	</size>
	<segmented>0</segmented>
	<object>
		<name>J20</name>
		<pose>Unspecified</pose>
		<truncated>0</truncated>
		<difficult>0</difficult>
		<occluded>0</occluded>
		<bndbox>
			<xmin>115</xmin>
			<xmax>300</xmax>
			<ymin>90</ymin>
			<ymax>189</ymax>
		</bndbox>
	</object>
</annotation>
