<annotation>
	<folder></folder>
	<filename>276a8305dde97ae01e28fd9ebdae8565_jpg.rf.565731a2245135247d7d2ffc2f139f36.jpg</filename>
	<path>276a8305dde97ae01e28fd9ebdae8565_jpg.rf.565731a2245135247d7d2ffc2f139f36.jpg</path>
	<source>
		<database>roboflow.ai</database>
	</source>
	<size>
		<width>416</width>
		<height>416</height>
		<depth>3</depth>
	</size>
	<segmented>0</segmented>
	<object>
		<name>V22</name>
		<pose>Unspecified</pose>
		<truncated>0</truncated>
		<difficult>0</difficult>
		<occluded>0</occluded>
		<bndbox>
			<xmin>113</xmin>
			<xmax>144</xmax>
			<ymin>120</ymin>
			<ymax>139</ymax>
		</bndbox>
	</object>
	<object>
		<name>V22</name>
		<pose>Unspecified</pose>
		<truncated>0</truncated>
		<difficult>0</difficult>
		<occluded>0</occluded>
		<bndbox>
			<xmin>126</xmin>
			<xmax>152</xmax>
			<ymin>163</ymin>
			<ymax>185</ymax>
		</bndbox>
	</object>
	<object>
		<name>V22</name>
		<pose>Unspecified</pose>
		<truncated>0</truncated>
		<difficult>0</difficult>
		<occluded>0</occluded>
		<bndbox>
			<xmin>135</xmin>
			<xmax>162</xmax>
			<ymin>205</ymin>
			<ymax>231</ymax>
		</bndbox>
	</object>
	<object>
		<name>C130</name>
		<pose>Unspecified</pose>
		<truncated>0</truncated>
		<difficult>0</difficult>
		<occluded>0</occluded>
		<bndbox>
			<xmin>296</xmin>
			<xmax>417</xmax>
			<ymin>322</ymin>
			<ymax>357</ymax>
		</bndbox>
	</object>
</annotation>
