<annotation>
	<folder></folder>
	<filename>1c0707ee35bf5afa3436b696c1e2e2b6_jpg.rf.faf94afc48f129023bd03403a941f8e3.jpg</filename>
	<path>1c0707ee35bf5afa3436b696c1e2e2b6_jpg.rf.faf94afc48f129023bd03403a941f8e3.jpg</path>
	<source>
		<database>roboflow.ai</database>
	</source>
	<size>
		<width>416</width>
		<height>416</height>
		<depth>3</depth>
	</size>
	<segmented>0</segmented>
	<object>
		<name>B1</name>
		<pose>Unspecified</pose>
		<truncated>0</truncated>
		<difficult>0</difficult>
		<occluded>0</occluded>
		<bndbox>
			<xmin>106</xmin>
			<xmax>336</xmax>
			<ymin>94</ymin>
			<ymax>213</ymax>
		</bndbox>
	</object>
</annotation>
