<annotation>
	<folder></folder>
	<filename>0ee6a43e1923fb14ef405e84ef02b3b2_jpg.rf.f863d787c7f0ee21ac0e4b2b4b57715d.jpg</filename>
	<path>0ee6a43e1923fb14ef405e84ef02b3b2_jpg.rf.f863d787c7f0ee21ac0e4b2b4b57715d.jpg</path>
	<source>
		<database>roboflow.ai</database>
	</source>
	<size>
		<width>416</width>
		<height>416</height>
		<depth>3</depth>
	</size>
	<segmented>0</segmented>
	<object>
		<name>EF2000</name>
		<pose>Unspecified</pose>
		<truncated>0</truncated>
		<difficult>0</difficult>
		<occluded>0</occluded>
		<bndbox>
			<xmin>13</xmin>
			<xmax>326</xmax>
			<ymin>161</ymin>
			<ymax>393</ymax>
		</bndbox>
	</object>
	<object>
		<name>EF2000</name>
		<pose>Unspecified</pose>
		<truncated>0</truncated>
		<difficult>0</difficult>
		<occluded>0</occluded>
		<bndbox>
			<xmin>178</xmin>
			<xmax>395</xmax>
			<ymin>69</ymin>
			<ymax>179</ymax>
		</bndbox>
	</object>
	<object>
		<name>EF2000</name>
		<pose>Unspecified</pose>
		<truncated>0</truncated>
		<difficult>0</difficult>
		<occluded>0</occluded>
		<bndbox>
			<xmin>205</xmin>
			<xmax>382</xmax>
			<ymin>45</ymin>
			<ymax>128</ymax>
		</bndbox>
	</object>
</annotation>
