<annotation>
	<folder></folder>
	<filename>f7db18b610bea828b40728d88ae6f276_jpg.rf.2947ef889d7f4820f8c5f0fe03a9a3b3.jpg</filename>
	<path>f7db18b610bea828b40728d88ae6f276_jpg.rf.2947ef889d7f4820f8c5f0fe03a9a3b3.jpg</path>
	<source>
		<database>roboflow.ai</database>
	</source>
	<size>
		<width>416</width>
		<height>416</height>
		<depth>3</depth>
	</size>
	<segmented>0</segmented>
	<object>
		<name>Be200</name>
		<pose>Unspecified</pose>
		<truncated>0</truncated>
		<difficult>0</difficult>
		<occluded>0</occluded>
		<bndbox>
			<xmin>318</xmin>
			<xmax>358</xmax>
			<ymin>6</ymin>
			<ymax>55</ymax>
		</bndbox>
	</object>
</annotation>
