<annotation>
	<folder></folder>
	<filename>74dd0d60064049c45e4b049a3648d804_jpg.rf.93db192772b505f173ad4ef4812537f4.jpg</filename>
	<path>74dd0d60064049c45e4b049a3648d804_jpg.rf.93db192772b505f173ad4ef4812537f4.jpg</path>
	<source>
		<database>roboflow.ai</database>
	</source>
	<size>
		<width>416</width>
		<height>416</height>
		<depth>3</depth>
	</size>
	<segmented>0</segmented>
	<object>
		<name>F35</name>
		<pose>Unspecified</pose>
		<truncated>0</truncated>
		<difficult>0</difficult>
		<occluded>0</occluded>
		<bndbox>
			<xmin>277</xmin>
			<xmax>345</xmax>
			<ymin>195</ymin>
			<ymax>339</ymax>
		</bndbox>
	</object>
</annotation>
