<annotation>
	<folder></folder>
	<filename>157ba41929e9a735be8a87725e8dbf69_jpg.rf.010e64cfc2ebb8c80cc9a94915f8dcc6.jpg</filename>
	<path>157ba41929e9a735be8a87725e8dbf69_jpg.rf.010e64cfc2ebb8c80cc9a94915f8dcc6.jpg</path>
	<source>
		<database>roboflow.ai</database>
	</source>
	<size>
		<width>416</width>
		<height>416</height>
		<depth>3</depth>
	</size>
	<segmented>0</segmented>
	<object>
		<name>Mirage2000</name>
		<pose>Unspecified</pose>
		<truncated>0</truncated>
		<difficult>0</difficult>
		<occluded>0</occluded>
		<bndbox>
			<xmin>337</xmin>
			<xmax>379</xmax>
			<ymin>277</ymin>
			<ymax>378</ymax>
		</bndbox>
	</object>
	<object>
		<name>Mirage2000</name>
		<pose>Unspecified</pose>
		<truncated>0</truncated>
		<difficult>0</difficult>
		<occluded>0</occluded>
		<bndbox>
			<xmin>264</xmin>
			<xmax>306</xmax>
			<ymin>161</ymin>
			<ymax>261</ymax>
		</bndbox>
	</object>
	<object>
		<name>Mirage2000</name>
		<pose>Unspecified</pose>
		<truncated>0</truncated>
		<difficult>0</difficult>
		<occluded>0</occluded>
		<bndbox>
			<xmin>197</xmin>
			<xmax>238</xmax>
			<ymin>239</ymin>
			<ymax>337</ymax>
		</bndbox>
	</object>
	<object>
		<name>Mirage2000</name>
		<pose>Unspecified</pose>
		<truncated>0</truncated>
		<difficult>0</difficult>
		<occluded>0</occluded>
		<bndbox>
			<xmin>49</xmin>
			<xmax>91</xmax>
			<ymin>252</ymin>
			<ymax>351</ymax>
		</bndbox>
	</object>
	<object>
		<name>Mirage2000</name>
		<pose>Unspecified</pose>
		<truncated>0</truncated>
		<difficult>0</difficult>
		<occluded>0</occluded>
		<bndbox>
			<xmin>137</xmin>
			<xmax>179</xmax>
			<ymin>132</ymin>
			<ymax>231</ymax>
		</bndbox>
	</object>
	<object>
		<name>Mirage2000</name>
		<pose>Unspecified</pose>
		<truncated>0</truncated>
		<difficult>0</difficult>
		<occluded>0</occluded>
		<bndbox>
			<xmin>212</xmin>
			<xmax>254</xmax>
			<ymin>42</ymin>
			<ymax>143</ymax>
		</bndbox>
	</object>
</annotation>
