<annotation>
	<folder></folder>
	<filename>3e301901474d54cf4cfcaefcc7ddf7ab_jpg.rf.696118b75725043f4cfa4037c5dc446c.jpg</filename>
	<path>3e301901474d54cf4cfcaefcc7ddf7ab_jpg.rf.696118b75725043f4cfa4037c5dc446c.jpg</path>
	<source>
		<database>roboflow.ai</database>
	</source>
	<size>
		<width>416</width>
		<height>416</height>
		<depth>3</depth>
	</size>
	<segmented>0</segmented>
	<object>
		<name>SR71</name>
		<pose>Unspecified</pose>
		<truncated>0</truncated>
		<difficult>0</difficult>
		<occluded>0</occluded>
		<bndbox>
			<xmin>38</xmin>
			<xmax>385</xmax>
			<ymin>18</ymin>
			<ymax>208</ymax>
		</bndbox>
	</object>
	<object>
		<name>Mig31</name>
		<pose>Unspecified</pose>
		<truncated>0</truncated>
		<difficult>0</difficult>
		<occluded>0</occluded>
		<bndbox>
			<xmin>88</xmin>
			<xmax>397</xmax>
			<ymin>228</ymin>
			<ymax>409</ymax>
		</bndbox>
	</object>
</annotation>
