<annotation>
	<folder></folder>
	<filename>58b77d97c8886ce89a0850bf918dad9f_jpg.rf.b2d6287f4920335e2a1c08eadfc47d4c.jpg</filename>
	<path>58b77d97c8886ce89a0850bf918dad9f_jpg.rf.b2d6287f4920335e2a1c08eadfc47d4c.jpg</path>
	<source>
		<database>roboflow.ai</database>
	</source>
	<size>
		<width>416</width>
		<height>416</height>
		<depth>3</depth>
	</size>
	<segmented>0</segmented>
	<object>
		<name>AG600</name>
		<pose>Unspecified</pose>
		<truncated>0</truncated>
		<difficult>0</difficult>
		<occluded>0</occluded>
		<bndbox>
			<xmin>55</xmin>
			<xmax>269</xmax>
			<ymin>115</ymin>
			<ymax>206</ymax>
		</bndbox>
	</object>
</annotation>
