<annotation>
	<folder></folder>
	<filename>e18a5eaaed53142dbf8c3f608abdba5a_jpg.rf.451c84cbb73127c5a85b522bc52aa4e3.jpg</filename>
	<path>e18a5eaaed53142dbf8c3f608abdba5a_jpg.rf.451c84cbb73127c5a85b522bc52aa4e3.jpg</path>
	<source>
		<database>roboflow.ai</database>
	</source>
	<size>
		<width>416</width>
		<height>416</height>
		<depth>3</depth>
	</size>
	<segmented>0</segmented>
	<object>
		<name>YF23</name>
		<pose>Unspecified</pose>
		<truncated>0</truncated>
		<difficult>0</difficult>
		<occluded>0</occluded>
		<bndbox>
			<xmin>2</xmin>
			<xmax>416</xmax>
			<ymin>4</ymin>
			<ymax>263</ymax>
		</bndbox>
	</object>
</annotation>
