<annotation>
	<folder></folder>
	<filename>3d5ed12f0a33325f5fb97a02807bbb60_jpg.rf.246f40963c5c438852591c9a51a4bf74.jpg</filename>
	<path>3d5ed12f0a33325f5fb97a02807bbb60_jpg.rf.246f40963c5c438852591c9a51a4bf74.jpg</path>
	<source>
		<database>roboflow.ai</database>
	</source>
	<size>
		<width>416</width>
		<height>416</height>
		<depth>3</depth>
	</size>
	<segmented>0</segmented>
	<object>
		<name>A10</name>
		<pose>Unspecified</pose>
		<truncated>0</truncated>
		<difficult>0</difficult>
		<occluded>0</occluded>
		<bndbox>
			<xmin>91</xmin>
			<xmax>126</xmax>
			<ymin>64</ymin>
			<ymax>74</ymax>
		</bndbox>
	</object>
</annotation>
