<annotation>
	<folder></folder>
	<filename>f4a1f593b068f1f90c1676d56f3aebf0_jpg.rf.aa2434f58a2a0badb70f6ed314e22cbc.jpg</filename>
	<path>f4a1f593b068f1f90c1676d56f3aebf0_jpg.rf.aa2434f58a2a0badb70f6ed314e22cbc.jpg</path>
	<source>
		<database>roboflow.ai</database>
	</source>
	<size>
		<width>416</width>
		<height>416</height>
		<depth>3</depth>
	</size>
	<segmented>0</segmented>
	<object>
		<name>C5</name>
		<pose>Unspecified</pose>
		<truncated>0</truncated>
		<difficult>0</difficult>
		<occluded>0</occluded>
		<bndbox>
			<xmin>35</xmin>
			<xmax>357</xmax>
			<ymin>205</ymin>
			<ymax>342</ymax>
		</bndbox>
	</object>
</annotation>
