<annotation>
	<folder></folder>
	<filename>4be5ad500733bb8810d6c7005ac225c3_jpg.rf.94cf78f588cb62317da1e4851acc907c.jpg</filename>
	<path>4be5ad500733bb8810d6c7005ac225c3_jpg.rf.94cf78f588cb62317da1e4851acc907c.jpg</path>
	<source>
		<database>roboflow.ai</database>
	</source>
	<size>
		<width>416</width>
		<height>416</height>
		<depth>3</depth>
	</size>
	<segmented>0</segmented>
	<object>
		<name>A10</name>
		<pose>Unspecified</pose>
		<truncated>0</truncated>
		<difficult>0</difficult>
		<occluded>0</occluded>
		<bndbox>
			<xmin>40</xmin>
			<xmax>60</xmax>
			<ymin>333</ymin>
			<ymax>372</ymax>
		</bndbox>
	</object>
	<object>
		<name>A10</name>
		<pose>Unspecified</pose>
		<truncated>0</truncated>
		<difficult>0</difficult>
		<occluded>0</occluded>
		<bndbox>
			<xmin>79</xmin>
			<xmax>101</xmax>
			<ymin>288</ymin>
			<ymax>323</ymax>
		</bndbox>
	</object>
	<object>
		<name>A10</name>
		<pose>Unspecified</pose>
		<truncated>0</truncated>
		<difficult>0</difficult>
		<occluded>0</occluded>
		<bndbox>
			<xmin>329</xmin>
			<xmax>345</xmax>
			<ymin>35</ymin>
			<ymax>65</ymax>
		</bndbox>
	</object>
</annotation>
