<annotation>
	<folder></folder>
	<filename>d3469aed415fd004bc0e6c40c8c56cc4_jpg.rf.6575df0f4ddd2582f2358327aeed78d0.jpg</filename>
	<path>d3469aed415fd004bc0e6c40c8c56cc4_jpg.rf.6575df0f4ddd2582f2358327aeed78d0.jpg</path>
	<source>
		<database>roboflow.ai</database>
	</source>
	<size>
		<width>416</width>
		<height>416</height>
		<depth>3</depth>
	</size>
	<segmented>0</segmented>
	<object>
		<name>B1</name>
		<pose>Unspecified</pose>
		<truncated>0</truncated>
		<difficult>0</difficult>
		<occluded>0</occluded>
		<bndbox>
			<xmin>217</xmin>
			<xmax>268</xmax>
			<ymin>264</ymin>
			<ymax>284</ymax>
		</bndbox>
	</object>
	<object>
		<name>B1</name>
		<pose>Unspecified</pose>
		<truncated>0</truncated>
		<difficult>0</difficult>
		<occluded>0</occluded>
		<bndbox>
			<xmin>142</xmin>
			<xmax>219</xmax>
			<ymin>291</ymin>
			<ymax>329</ymax>
		</bndbox>
	</object>
	<object>
		<name>F16</name>
		<pose>Unspecified</pose>
		<truncated>0</truncated>
		<difficult>0</difficult>
		<occluded>0</occluded>
		<bndbox>
			<xmin>162</xmin>
			<xmax>201</xmax>
			<ymin>344</ymin>
			<ymax>365</ymax>
		</bndbox>
	</object>
</annotation>
