<annotation>
	<folder></folder>
	<filename>1b8c5714df7f4ca1554eb276452642d4_jpg.rf.ac6854e030ec08efe29e679438fd3987.jpg</filename>
	<path>1b8c5714df7f4ca1554eb276452642d4_jpg.rf.ac6854e030ec08efe29e679438fd3987.jpg</path>
	<source>
		<database>roboflow.ai</database>
	</source>
	<size>
		<width>416</width>
		<height>416</height>
		<depth>3</depth>
	</size>
	<segmented>0</segmented>
	<object>
		<name>Rafale</name>
		<pose>Unspecified</pose>
		<truncated>0</truncated>
		<difficult>0</difficult>
		<occluded>0</occluded>
		<bndbox>
			<xmin>226</xmin>
			<xmax>269</xmax>
			<ymin>240</ymin>
			<ymax>283</ymax>
		</bndbox>
	</object>
	<object>
		<name>Rafale</name>
		<pose>Unspecified</pose>
		<truncated>0</truncated>
		<difficult>0</difficult>
		<occluded>0</occluded>
		<bndbox>
			<xmin>235</xmin>
			<xmax>271</xmax>
			<ymin>146</ymin>
			<ymax>225</ymax>
		</bndbox>
	</object>
</annotation>
