<annotation>
	<folder></folder>
	<filename>c18ee70bf0f56a2c2b3d6e17bf960540_jpg.rf.6556f2097682b457d058bd88c72928fa.jpg</filename>
	<path>c18ee70bf0f56a2c2b3d6e17bf960540_jpg.rf.6556f2097682b457d058bd88c72928fa.jpg</path>
	<source>
		<database>roboflow.ai</database>
	</source>
	<size>
		<width>416</width>
		<height>416</height>
		<depth>3</depth>
	</size>
	<segmented>0</segmented>
	<object>
		<name>XB70</name>
		<pose>Unspecified</pose>
		<truncated>0</truncated>
		<difficult>0</difficult>
		<occluded>0</occluded>
		<bndbox>
			<xmin>30</xmin>
			<xmax>346</xmax>
			<ymin>126</ymin>
			<ymax>201</ymax>
		</bndbox>
	</object>
</annotation>
