<annotation>
	<folder></folder>
	<filename>623_jpg.rf.c311d516d9280a3f1e7df6df93f36eff.jpg</filename>
	<path>623_jpg.rf.c311d516d9280a3f1e7df6df93f36eff.jpg</path>
	<source>
		<database>roboflow.com</database>
	</source>
	<size>
		<width>640</width>
		<height>640</height>
		<depth>3</depth>
	</size>
	<segmented>0</segmented>
	<object>
		<name>Tank</name>
		<pose>Unspecified</pose>
		<truncated>0</truncated>
		<difficult>0</difficult>
		<occluded>0</occluded>
		<bndbox>
			<xmin>1</xmin>
			<xmax>641</xmax>
			<ymin>1</ymin>
			<ymax>496</ymax>
		</bndbox>
	</object>
</annotation>
