<annotation>
	<folder></folder>
	<filename>109_jpg.rf.9a2fb9e6921e31815a2d3c376524a5d3.jpg</filename>
	<path>109_jpg.rf.9a2fb9e6921e31815a2d3c376524a5d3.jpg</path>
	<source>
		<database>roboflow.com</database>
	</source>
	<size>
		<width>640</width>
		<height>640</height>
		<depth>3</depth>
	</size>
	<segmented>0</segmented>
	<object>
		<name>Tank</name>
		<pose>Unspecified</pose>
		<truncated>0</truncated>
		<difficult>0</difficult>
		<occluded>0</occluded>
		<bndbox>
			<xmin>1</xmin>
			<xmax>641</xmax>
			<ymin>13</ymin>
			<ymax>590</ymax>
		</bndbox>
	</object>
</annotation>
