<annotation>
	<folder></folder>
	<filename>image_00145_jpeg_jpg.rf.88a36dbf78ab67bb5df9d1fe1984dba4.jpg</filename>
	<path>image_00145_jpeg_jpg.rf.88a36dbf78ab67bb5df9d1fe1984dba4.jpg</path>
	<source>
		<database>roboflow.com</database>
	</source>
	<size>
		<width>640</width>
		<height>640</height>
		<depth>3</depth>
	</size>
	<segmented>0</segmented>
	<object>
		<name>Helicopter</name>
		<pose>Unspecified</pose>
		<truncated>0</truncated>
		<difficult>0</difficult>
		<occluded>0</occluded>
		<bndbox>
			<xmin>293</xmin>
			<xmax>347</xmax>
			<ymin>259</ymin>
			<ymax>310</ymax>
		</bndbox>
	</object>
	<object>
		<name>Helicopter</name>
		<pose>Unspecified</pose>
		<truncated>0</truncated>
		<difficult>0</difficult>
		<occluded>0</occluded>
		<bndbox>
			<xmin>251</xmin>
			<xmax>320</xmax>
			<ymin>99</ymin>
			<ymax>163</ymax>
		</bndbox>
	</object>
	<object>
		<name>Helicopter</name>
		<pose>Unspecified</pose>
		<truncated>0</truncated>
		<difficult>0</difficult>
		<occluded>0</occluded>
		<bndbox>
			<xmin>153</xmin>
			<xmax>257</xmax>
			<ymin>195</ymin>
			<ymax>275</ymax>
		</bndbox>
	</object>
</annotation>
