<annotation>
	<folder></folder>
	<filename>642_jpg.rf.2391cf6c8a0b36d1ec45bb03b48f5f84.jpg</filename>
	<path>642_jpg.rf.2391cf6c8a0b36d1ec45bb03b48f5f84.jpg</path>
	<source>
		<database>roboflow.com</database>
	</source>
	<size>
		<width>640</width>
		<height>640</height>
		<depth>3</depth>
	</size>
	<segmented>0</segmented>
	<object>
		<name>Tank</name>
		<pose>Unspecified</pose>
		<truncated>0</truncated>
		<difficult>0</difficult>
		<occluded>0</occluded>
		<bndbox>
			<xmin>3</xmin>
			<xmax>500</xmax>
			<ymin>135</ymin>
			<ymax>582</ymax>
		</bndbox>
	</object>
</annotation>
