<annotation>
	<folder></folder>
	<filename>190_jpg.rf.d669cd00e7f4f65c08d3e641f2228de6.jpg</filename>
	<path>190_jpg.rf.d669cd00e7f4f65c08d3e641f2228de6.jpg</path>
	<source>
		<database>roboflow.com</database>
	</source>
	<size>
		<width>640</width>
		<height>640</height>
		<depth>3</depth>
	</size>
	<segmented>0</segmented>
	<object>
		<name>Tank</name>
		<pose>Unspecified</pose>
		<truncated>0</truncated>
		<difficult>0</difficult>
		<occluded>0</occluded>
		<bndbox>
			<xmin>1</xmin>
			<xmax>641</xmax>
			<ymin>1</ymin>
			<ymax>641</ymax>
		</bndbox>
	</object>
</annotation>
